pysma/__init__.py
pysma/const.py
pysma/definitions/__init__.py
pysma/definitions/webconnect.py
pysma/exceptions.py
pysma/helpers.py
pysma/l10n/cs-CS.json
pysma/l10n/de-DE.json
pysma/l10n/el-EL.json
pysma/l10n/en-US.json
pysma/l10n/es-ES.json
pysma/l10n/fr-FR.json
pysma/l10n/hu-HU.json
pysma/l10n/it-IT.json
pysma/l10n/ja-JP.json
pysma/l10n/ko-KR.json
pysma/l10n/nl-NL.json
pysma/l10n/pl-PL.json
pysma/l10n/pt-PT.json
pysma/l10n/sv-SE.json
pysma/l10n/th-TH.json
pysma/py.typed
pysma/sensor.py
pysma/sma_webconnect.py
pysma-1.0.4.dist-info/licenses/LICENSE
pysma-1.0.4.dist-info/WHEEL
pysma-1.0.4.dist-info/METADATA
pysma-1.0.4.dist-info/RECORD
