Metadata-Version: 2.4
Name: pysma
Version: 1.0.4
Summary: Library to interface an SMA Solar devices
Author: Johann Kellerman, René Klomp
Author-email: Johann Kellerman <kellerza@gmail.com>
License-Expression: MIT
License-File: LICENSE
Classifier: Programming Language :: Python :: 3 :: Only
Classifier: Programming Language :: Python :: 3.12
Classifier: Programming Language :: Python :: 3.13
Classifier: Programming Language :: Python :: 3.14
Requires-Dist: aiohttp>=3,<4
Requires-Dist: attrs
Requires-Dist: jmespath
Requires-Python: >=3.12
Project-URL: Source, https://github.com/kellerza/pysma
